{
  "ID": "922b501a-9e55-4da9-b4db-8ba530f5e6a9",
  "Version": "2.3.4",
  "Name": "WaitUILayer",
  "Content": {
    "Content": {
      "Animation": {
        "Duration": 0,
        "Speed": 1.0,
        "Timelines": [],
        "ctype": "TimelineActionData"
      },
      "AnimationList": [],
      "ObjectData": {
        "Tag": 124,
        "Children": [
          {
            "ClipAble": false,
            "ComboBoxIndex": 1,
            "SingleColor": {
              "R": 0,
              "G": 0,
              "B": 0
            },
            "FirstColor": {
              "R": 150,
              "G": 200
            },
            "EndColor": {},
            "ColorVector": {
              "ScaleY": 1.0
            },
            "Scale9Width": 1,
            "Scale9Height": 1,
            "AnchorPoint": {
              "ScaleX": 0.5,
              "ScaleY": 0.5
            },
            "Position": {
              "X": 480.0,
              "Y": 320.0
            },
            "Scale": {
              "ScaleX": 1.0,
              "ScaleY": 1.0
            },
            "CColor": {},
            "IconVisible": false,
            "PrePosition": {
              "X": 0.5,
              "Y": 0.5
            },
            "PreSize": {
              "X": 1.1833,
              "Y": 1.0
            },
            "LeftMargin": -88.0,
            "RightMargin": -88.0,
            "Tag": 554,
            "ActionTag": 662063672,
            "Size": {
              "X": 1136.0,
              "Y": 640.0
            },
            "Alpha": 104,
            "Name": "maskLayer",
            "ctype": "PanelObjectData"
          },
          {
            "ClipAble": false,
            "BackColorAlpha": 102,
            "SingleColor": {
              "R": 150,
              "G": 200
            },
            "FirstColor": {
              "R": 150,
              "G": 200
            },
            "EndColor": {},
            "ColorVector": {
              "ScaleY": 1.0
            },
            "Scale9Width": 1,
            "Scale9Height": 1,
            "TouchEnable": true,
            "AnchorPoint": {
              "ScaleX": 0.5,
              "ScaleY": 0.5
            },
            "Position": {
              "X": 480.0,
              "Y": 320.0
            },
            "Scale": {
              "ScaleX": 1.0,
              "ScaleY": 1.0
            },
            "CColor": {},
            "IconVisible": false,
            "PrePosition": {
              "X": 0.5,
              "Y": 0.5
            },
            "PreSize": {
              "X": 1.1833,
              "Y": 1.0
            },
            "LeftMargin": -88.0,
            "RightMargin": -88.0,
            "Tag": 555,
            "ActionTag": -2037570246,
            "Size": {
              "X": 1136.0,
              "Y": 640.0
            },
            "Name": "touchLayer",
            "ctype": "PanelObjectData"
          },
          {
            "ClipAble": false,
            "BackColorAlpha": 102,
            "SingleColor": {
              "R": 150,
              "G": 200
            },
            "FirstColor": {
              "R": 150,
              "G": 200
            },
            "EndColor": {},
            "ColorVector": {
              "ScaleY": 1.0
            },
            "Scale9Width": 1,
            "Scale9Height": 1,
            "TouchEnable": true,
            "AnchorPoint": {
              "ScaleX": 0.5,
              "ScaleY": 0.5
            },
            "Position": {
              "X": 480.0,
              "Y": 320.0
            },
            "Scale": {
              "ScaleX": 1.0,
              "ScaleY": 1.0
            },
            "CColor": {},
            "IconVisible": false,
            "PrePosition": {
              "X": 0.5,
              "Y": 0.5
            },
            "PreSize": {
              "X": 1.1833,
              "Y": 1.0
            },
            "LeftMargin": -88.0,
            "RightMargin": -88.0,
            "Tag": 553,
            "Children": [
              {
                "FileData": {
                  "Type": "PlistSubImage",
                  "Path": "image_loading_bar_bg.png",
                  "Plist": "plaza/plaza.plist"
                },
                "Scale9Enable": true,
                "Scale9OriginX": 134,
                "Scale9OriginY": 29,
                "Scale9Width": 140,
                "Scale9Height": 32,
                "AnchorPoint": {
                  "ScaleX": 0.5,
                  "ScaleY": 0.5
                },
                "Position": {
                  "X": 568.0,
                  "Y": 150.0
                },
                "Scale": {
                  "ScaleX": 1.0,
                  "ScaleY": 1.0
                },
                "CColor": {},
                "IconVisible": false,
                "PrePosition": {
                  "X": 0.5,
                  "Y": 0.2344
                },
                "PreSize": {
                  "X": 0.5722,
                  "Y": 0.1406
                },
                "LeftMargin": 243.0,
                "RightMargin": 243.0,
                "TopMargin": 445.0,
                "BottomMargin": 105.0,
                "Tag": 1428,
                "ActionTag": -487360006,
                "Size": {
                  "X": 650.0,
                  "Y": 90.0
                },
                "Name": "Image_wait_bk",
                "ctype": "ImageViewObjectData"
              },
              {
                "IsCustomSize": true,
                "FontSize": 20,
                "LabelText": "当前服务器正处于维护中，请留意官方公告或者稍后再试，给您带来的不便深表歉意！客服qq:22343234",
                "FontResource": {
                  "Type": "Normal",
                  "Path": "fnt/normal.TTF",
                  "Plist": ""
                },
                "VerticalAlignmentType": "VT_Center",
                "OutlineColor": {
                  "G": 0,
                  "B": 0
                },
                "ShadowColor": {
                  "R": 110,
                  "G": 110,
                  "B": 110
                },
                "ShadowOffsetX": 2.0,
                "ShadowOffsetY": -2.0,
                "AnchorPoint": {
                  "ScaleX": 0.5,
                  "ScaleY": 0.5
                },
                "Position": {
                  "X": 587.9775,
                  "Y": 149.7082
                },
                "Scale": {
                  "ScaleX": 1.0,
                  "ScaleY": 1.0
                },
                "CColor": {},
                "IconVisible": false,
                "PrePosition": {
                  "X": 0.5176,
                  "Y": 0.2339
                },
                "PreSize": {
                  "X": 0.4225,
                  "Y": 0.1172
                },
                "LeftMargin": 347.9775,
                "RightMargin": 308.0225,
                "TopMargin": 452.7918,
                "BottomMargin": 112.2082,
                "Tag": 1429,
                "ActionTag": 1360240613,
                "Size": {
                  "X": 480.0,
                  "Y": 75.0
                },
                "Name": "text_wait_info",
                "ctype": "TextObjectData"
              },
              {
                "FileData": {
                  "Type": "PlistSubImage",
                  "Path": "image_loading_bar_flower.png",
                  "Plist": "plaza/plaza.plist"
                },
                "Scale9OriginX": 19,
                "Scale9OriginY": 20,
                "Scale9Width": 22,
                "Scale9Height": 22,
                "AnchorPoint": {
                  "ScaleX": 0.5,
                  "ScaleY": 0.5
                },
                "Position": {
                  "X": 300.0,
                  "Y": 150.0
                },
                "Scale": {
                  "ScaleX": 1.0,
                  "ScaleY": 1.0
                },
                "CColor": {},
                "IconVisible": false,
                "PrePosition": {
                  "X": 0.2641,
                  "Y": 0.2344
                },
                "PreSize": {
                  "X": 0.0528,
                  "Y": 0.0969
                },
                "LeftMargin": 270.0,
                "RightMargin": 806.0,
                "TopMargin": 459.0,
                "BottomMargin": 119.0,
                "Tag": 1430,
                "ActionTag": -69510683,
                "Size": {
                  "X": 60.0,
                  "Y": 62.0
                },
                "Name": "Image_wait_animation",
                "ctype": "ImageViewObjectData"
              }
            ],
            "ActionTag": -876177509,
            "Size": {
              "X": 1136.0,
              "Y": 640.0
            },
            "Name": "Panel_1",
            "ctype": "PanelObjectData"
          }
        ],
        "Size": {
          "X": 960.0,
          "Y": 640.0
        },
        "Name": "Layer",
        "ctype": "LayerObjectData"
      },
      "UsedResources": [
        "fnt/normal.TTF",
        "plaza/plaza.plist",
        "plaza/plaza.png"
      ],
      "ctype": "GameFileData"
    }
  },
  "Type": "Layer"
}